Metadata-Version: 2.4
Name: peek-worker-service
Version: 5.0.4
Summary: Peek Worker Service - distributed multiprocessing support for Peek
Author-email: Synerty <contact@synerty.com>
Project-URL: Homepage, https://github.com/Synerty/peek-worker-service
Keywords: Peek,Python,Platform,synerty
License-File: LICENSE
Requires-Dist: peek-plugin-base==5.0.4
Requires-Dist: peek-platform==5.0.4
Requires-Dist: valkey
Dynamic: license-file
